src/__init__.py
src/detector.py
src/report_generator.py
src/utils.py
tests/__init__.py
tests/test_detector.py
tests/test_report_generator.py
dns_poisoning_detector-0.1.0.dist-info/LICENSE
dns_poisoning_detector-0.1.0.dist-info/METADATA
dns_poisoning_detector-0.1.0.dist-info/WHEEL
dns_poisoning_detector-0.1.0.dist-info/entry_points.txt
dns_poisoning_detector-0.1.0.dist-info/top_level.txt
dns_poisoning_detector-0.1.0.dist-info/RECORD
